exp_phase1_a/__init__.py
exp_phase1_a/data_prepare.py
exp_phase1_a/make_dataset_model.py
exp_phase1_a/predict.py
exp_phase1_a/training_model.py
exp_phase1_a-0.1.2.dist-info/METADATA
exp_phase1_a-0.1.2.dist-info/WHEEL
exp_phase1_a-0.1.2.dist-info/RECORD
